Metadata-Version: 1.0
Name: Heeelllooooo
Version: 0.1.2
Summary: Pokochasz tą paczke od pierwszych chwil <3 <3 <3
Home-page: UNKNOWN
Author: Marcin Trzaska
Author-email: maniu190.94@o2.pl
License: UNKNOWN
Platform: UNKNOWN
